[
  {
    "language": "Python",
    "average_salary": "$96,890.00",
    "user_love": "67%",
    "difficulty_level": "easy"
  },
  {
    "language": "C#",
    "average_salary": "$84,243.00",
    "user_love": "60%",
    "difficulty_level": "moderate"
  },
  {
    "language": "C++",
    "average_salary": "$89,736.00",
    "user_love": "43%",
    "difficulty_level": "hard"
  },
  {
    "language": "JavaScript",
    "average_salary": "$90,864.00",
    "user_love": "58%",
    "difficulty_level": "easy"
  },
  {
    "language": "PHP",
    "average_salary": "$79,499.00",
    "user_love": "37%",
    "difficulty_level": "easy"
  },
  {
    "language": "Swift",
    "average_salary": "$89,736.00",
    "user_love": "60%",
    "difficulty_level": "moderate"
  },
  {
    "language": "Java",
    "average_salary": "$93,118.00",
    "user_love": "44%",
    "difficulty_level": "moderate"
  },
  {
    "language": "Go",
    "average_salary": "$99,627.00",
    "user_love": "62%",
    "difficulty_level": "easy"
  },
  {
    "language": "SQL",
    "average_salary": "$88,938.00",
    "user_love": "57%",
    "difficulty_level": "easy"
  },
  {
    "language": "Ruby",
    "average_salary": "$89,872.00",
    "user_love": "43%",
    "difficulty_level": "easy"
  }
]